<?xml version="1.0" encoding="UTF-8"?>
<AgentMessage to="managementserver.localhost" from="xp1001@localhost/xp1001"
	type="Response" logLevel="">
	<Response>
		<Header serviceName='DeviceAdmin' type='RPC' requestName='Reboot'
			userJID='xp1001@localhost/xp1001' requestNID='1234' state='200'>
			<ClientData>cd123</ClientData>
			<ClientCallback></ClientCallback>
		</Header>
		<Data>
			<RebootDeviceResponseData>
     				<RebootDevice/>
    			</RebootDeviceResponseData>
		</Data>
	</Response>
</AgentMessage>
