<serialization jsxversion="3.9" xmlns="urn:tibco.com/v3.0">
  <name></name>
  <icon></icon>
  <description></description>
  <onBeforeDeserialize></onBeforeDeserialize>
  <onAfterDeserialize></onAfterDeserialize>
  <object type="com.ipvs.gui.Pagination">
    <variants jsxoverflow="2"></variants>
    <strings jsxname="blkPagination" jsxwidth="100%" jsxheight="100%" jsxtextalign="center" jsxpadding="5 0 5 0" jsxbgcolor="#383838" jsxborder="border-top:solid 1px #484848" jsxcolor=""></strings>
    <object type="jsx3.gui.ImageButton">
      <variants jsxwidth="16" jsxheight="16" jsxprefetch="1" jsxtype="0" jsxstate="0" jsxenabled="0" jsxleft="45" jsxrelativeposition="0" jsxtop="9"></variants>
      <strings jsxname="btnPageFirst" jsximage="images/buttons/btnFirstPageUp.png" jsxdisabledimage="images/buttons/btnFirstPageDsbl.png" jsxmargin="0 8 0 8" jsxtext="First page" jsxtip="First page" jsxonimage="images/buttons/btnFirstPageUp.png" jsxdisplay=""></strings>
    </object>
    <object type="jsx3.gui.ImageButton">
      <variants jsxwidth="16" jsxheight="16" jsxprefetch="1" jsxtype="0" jsxstate="0" jsxenabled="0" jsxleft="80" jsxrelativeposition="0" jsxtop="9"></variants>
      <strings jsxname="btnPagePrev" jsximage="images/buttons/btnPreviousPageUp.png" jsxdisabledimage="images/buttons/btnPreviousPageDsbl.png" jsxmargin="0 40 0 20" jsxtext="Previous page" jsxtip="Previous page" jsxonimage="images/buttons/btnPreviousPageUp.png" jsxdisplay=""></strings>
    </object>
    <object type="jsx3.gui.ImageButton">
      <variants jsxwidth="16" jsxheight="16" jsxprefetch="1" jsxtype="0" jsxstate="0" jsxenabled="0" jsxrelativeposition="0" jsxleft="164" jsxtop="9"></variants>
      <strings jsxname="btnPageRefresh" jsximage="images/buttons/btnPageRefreshUp.png" jsxdisabledimage="images/buttons/btnPageRefreshDsbl.png" jsxmargin="0 10 0 10" jsxtext="Refresh list" jsxtip="Refresh list" jsxonimage="images/buttons/btnPageRefreshOn.png" jsxdisplay=""></strings>
    </object>
    <object type="jsx3.gui.ImageButton">
      <variants jsxwidth="16" jsxheight="16" jsxprefetch="1" jsxtype="0" jsxstate="0" jsxenabled="0" jsxrelativeposition="0" jsxleft="246" jsxtop="9"></variants>
      <strings jsxname="btnPageNext" jsximage="images/buttons/btnNextPageUp.png" jsxdisabledimage="images/buttons/btnNextPageDsbl.png" jsxmargin="0 20 0 40" jsxtext="Next page" jsxtip="Next page" jsxonimage="images/buttons/btnNextPageUp.png" jsxdisplay=""></strings>
    </object>
    <object type="jsx3.gui.ImageButton">
      <variants jsxwidth="16" jsxheight="16" jsxprefetch="1" jsxtype="0" jsxstate="0" jsxenabled="0" jsxrelativeposition="0" jsxleft="282" jsxtop="9"></variants>
      <strings jsxname="btnPageLast" jsximage="images/buttons/btnLastPageUp.png" jsxdisabledimage="images/buttons/btnLastPageDsbl.png" jsxmargin="0 8 0 8" jsxtext="Last page" jsxtip="Last page" jsxonimage="images/buttons/btnLastPageUp.png" jsxdisplay=""></strings>
    </object>
  </object>
</serialization>