<serialization jsxversion="3.9" xmlns="urn:tibco.com/v3.0">
  <object type="jsx3.gui.Dialog">
    <variants jsxwidth="892" jsxheight="642" jsxzindex="5020" jsxwindowstate="1" jsxleft="0" jsxtop="0" jsxminx="650" jsxminy="400" jsxmodal="1"></variants>
    <strings jsxname="dlgName" jsxdisplay=""></strings>
    <dynamics jsxbgcolor="Dialog BG"></dynamics>
    <object type="jsx3.gui.WindowBar">
      <variants></variants>
      <strings jsxname="windowBar" jsxbgcolor="#cccccc" jsxtext="Dialog"></strings>
      <object type="jsx3.gui.ToolbarButton">
        <variants></variants>
        <strings jsxname="btnMinimize"></strings>
        <dynamics jsximage="@Min Icon" jsxtip="jsx3.gui.Dialog.min"></dynamics>
        <events jsxexecute="this.getAncestorOfType(jsx3.gui.Dialog).doToggleState();"></events>
      </object>
      <object type="jsx3.gui.ToolbarButton">
        <variants></variants>
        <strings jsxname="btnMaximize"></strings>
        <dynamics jsximage="@Max Icon" jsxtip="@Max Tip"></dynamics>
        <events jsxexecute="this.getAncestorOfType(jsx3.gui.Dialog).doMaximize(this);"></events>
      </object>
      <object type="jsx3.gui.ToolbarButton">
        <variants></variants>
        <strings jsxname="btnDialogCloseX"></strings>
        <dynamics jsximage="@Close Icon" jsxtip="jsx3.gui.Dialog.close"></dynamics>
        <events jsxexecute=""></events>
      </object>
    </object>
    <object type="jsx3.gui.Block">
      <variants jsxoverflow="1" jsxloadtype="1"></variants>
      <strings jsxname="blkDialogName" jsxwidth="100%" jsxheight="100%" jsxrelativeposition="1"></strings>
      <object type="jsx3.gui.LayoutGrid">
        <variants jsxrelativeposition="0" jsxleft="0" jsxtop="0" jsxoverflow="2"></variants>
        <strings jsxname="layoutRows" jsxrows="*,40" jsxwidth="100%" jsxheight="100%"></strings>
        <object type="jsx3.gui.Block">
          <variants jsxoverflow="2"></variants>
          <strings jsxname="blkDialogBody" jsxwidth="100%" jsxheight="100%" jsxborder="1px solid #efefef;1px solid #9898a5;1px solid #999999;1px solid #d8d8e5" jsxbgcolor="#e0e0e0"></strings>
          <object type="jsx3.gui.LayoutGrid">
            <variants jsxrelativeposition="0" jsxleft="0" jsxtop="0" jsxoverflow="2"></variants>
            <strings jsxname="layout ( | )" jsxcols="190,*" jsxwidth="100%" jsxheight="100%"></strings>
            <object type="jsx3.gui.Block">
              <variants jsxoverflow="2"></variants>
              <strings jsxname="blkLeftPanel" jsxwidth="100%" jsxheight="100%" jsxcolor="" jsxpadding="8 4 4 4" jsxbgcolor="#d9d9d9"></strings>
              <dynamics jsxborder="@No jsxborder"></dynamics>
              <object type="jsx3.gui.Block">
                <variants jsxoverflow="2" jsxheight="22"></variants>
                <strings jsxname="blkLbl" jsxwidth="100%" jsxrelativeposition="1" jsxmargin="4 0 4 0"></strings>
                <object type="jsx3.gui.Block">
                  <variants jsxrelativeposition="1" jsxoverflow="3" jsxfontsize="12"></variants>
                  <strings jsxheight="100%" jsxname="lblReports" jsxtext="Menu Label" jsxwidth="100%" jsxpadding="4 4 4 4" jsxcursor="hand" jsxfontweight="normal" jsxmargin=""></strings>
                  <events jsxclick="null;"></events>
                </object>
              </object>
              <object type="jsx3.gui.Block">
                <variants jsxoverflow="2" jsxheight="22"></variants>
                <strings jsxname="blkLbl" jsxwidth="100%" jsxrelativeposition="1" jsxmargin="4 0 4 0"></strings>
                <object type="jsx3.gui.Block">
                  <variants jsxrelativeposition="1" jsxoverflow="3" jsxfontsize="12"></variants>
                  <strings jsxheight="100%" jsxname="lblReports" jsxtext="Menu Label" jsxwidth="100%" jsxpadding="4 4 4 4" jsxcursor="hand" jsxfontweight="normal" jsxmargin=""></strings>
                  <events jsxclick="null;"></events>
                </object>
              </object>
              <object type="jsx3.gui.Block">
                <variants jsxoverflow="2" jsxheight="22"></variants>
                <strings jsxname="blkLbl" jsxwidth="100%" jsxrelativeposition="1" jsxmargin="4 0 4 0"></strings>
                <object type="jsx3.gui.Block">
                  <variants jsxrelativeposition="1" jsxoverflow="3" jsxfontsize="12"></variants>
                  <strings jsxheight="100%" jsxname="lblReports" jsxtext="Menu Label" jsxwidth="100%" jsxpadding="4 4 4 4" jsxcursor="hand" jsxfontweight="normal" jsxmargin=""></strings>
                  <events jsxclick="null;"></events>
                </object>
              </object>
              <object type="jsx3.gui.Block">
                <variants jsxoverflow="2" jsxheight="22"></variants>
                <strings jsxname="blkLbl" jsxwidth="100%" jsxrelativeposition="1" jsxmargin="4 0 4 0"></strings>
                <object type="jsx3.gui.Block">
                  <variants jsxrelativeposition="1" jsxoverflow="3" jsxfontsize="12"></variants>
                  <strings jsxheight="100%" jsxname="lblReports" jsxtext="Menu Label" jsxwidth="100%" jsxpadding="4 4 4 4" jsxcursor="hand" jsxfontweight="normal" jsxmargin=""></strings>
                  <events jsxclick="null;"></events>
                </object>
              </object>
            </object>
            <object type="jsx3.gui.Block">
              <variants jsxoverflow="3"></variants>
              <strings jsxname="blkRightPanel" jsxwidth="100%" jsxheight="100%" jsxdisplay="" jsxborder="border-left: solid 1px #999999" jsxbgcolor="#e5e5e5"></strings>
              <object type="jsx3.gui.Block">
                <variants jsxrelativeposition="0" jsxoverflow="3" jsxleft="0" jsxtop="0"></variants>
                <strings jsxname="blkDialogItem1" jsxwidth="100%" jsxheight="100%" jsxdisplay=""></strings>
                <dynamics jsxborder="@No jsxborder" jsxbgcolor="@Transparent BG"></dynamics>
                <object type="jsx3.gui.Block">
                  <variants jsxoverflow="2" jsxheight="35"></variants>
                  <strings jsxname="blkHeader" jsxwidth="100%" jsxbgcolor="#d9d9d9" jsxtextalign="left" jsxpadding="6 8 8 10" jsxborder="border-bottom: 1px solid #9898a5"></strings>
                  <object type="jsx3.gui.Block">
                    <variants jsxrelativeposition="1" jsxoverflow="3" jsxfontsize="16"></variants>
                    <strings jsxname="label" jsxtext="Preferences" jsxfontweight="normal" jsxmargin="0 20 0 0"></strings>
                  </object>
                </object>
                <object type="jsx3.gui.Block">
                  <variants jsxoverflow="3" jsxheight="400"></variants>
                  <strings jsxname="blkBody" jsxwidth="100%" jsxbgcolor="#e5e5e5" jsxcolor=""></strings>
                  <dynamics jsxpadding="@8Pixel" jsxborder="@No jsxborder"></dynamics>
                  <object type="jsx3.gui.Block">
                    <variants jsxoverflow="3" jsxheight="30"></variants>
                    <strings jsxname="blkFormSectionTitle" jsxwidth="100%" jsxrelativeposition="1" jsxtextalign="right" jsxpadding="6 6 6 6" jsxclassname="formSectionTitle" jsxdisplay=""></strings>
                    <object type="jsx3.gui.Block">
                      <variants jsxrelativeposition="0" jsxoverflow="3" jsxfontsize="13" jsxleft="11" jsxtop="6"></variants>
                      <strings jsxname="label" jsxtext="Max Concurrent Client Logins" jsxdisplay="" jsxfontweight="bold" jsxcolor="#164fa4"></strings>
                    </object>
                  </object>
                  <object type="jsx3.gui.Block">
                    <variants jsxoverflow="3" jsxheight="30"></variants>
                    <strings jsxname="blkName" jsxwidth="100%" jsxrelativeposition="1"></strings>
                    <object type="jsx3.gui.Block">
                      <variants jsxrelativeposition="0" jsxoverflow="3" jsxleft="15" jsxtop="19" jsxwidth="270" jsxfontsize="11"></variants>
                      <strings jsxname="label" jsxtext="Max number of concurrent Media Client Logins:" jsxdisplay="" jsxtextalign="right" jsxclassname="formLabel" jsxcolor=""></strings>
                    </object>
                    <object type="jsx3.gui.TextBox">
                      <variants jsxheight="20" jsxrelativeposition="0" jsxleft="291" jsxtop="17" jsxwidth="50" jsxenabled="1"></variants>
                      <strings jsxname="txtMaxClientLogins" jsxmargin="0 4 0 0" jsxdisplay="" jsxvalue="" jsxpadding="0 0 2 2" jsxclassname="formTextBox" jsxborder="1px solid #888888;1px solid #c1c1c1;1px solid #e1e1e1;1px solid #c1c1c1"></strings>
                    </object>
                    <object type="jsx3.gui.Block">
                      <variants jsxrelativeposition="0" jsxoverflow="3" jsxleft="351" jsxtop="21"></variants>
                      <strings jsxname="label" jsxtext="(Valid entry is 1 - 999)" jsxdisplay="" jsxcolor="" jsxclassname="helpText"></strings>
                    </object>
                    <object type="jsx3.gui.Button">
                      <variants jsxindex="0" jsxheight="20" jsxrelativeposition="0" jsxleft="260" jsxtop="104" jsxwidth="110" jsxenabled="1"></variants>
                      <strings jsxname="btnSetPreferences" jsxtext="Set Preferences" jsxmargin="0 4 0 0" jsxclassname="btnBlueGlass" jsxtip=""></strings>
                      <events jsxexecute=""></events>
                    </object>
                  </object>
                  <object type="jsx3.gui.Block">
                    <variants jsxoverflow="1" jsxwidth="550" jsxheight="380" jsxrelativeposition="0" jsxleft="4" jsxtop="231" jsxzindex="0"></variants>
                    <strings jsxname="block" jsxdisplay=""></strings>
                    <dynamics jsxbgcolor="@Transparent BG"></dynamics>
                  </object>
                </object>
              </object>
            </object>
          </object>
        </object>
        <object type="jsx3.gui.Block">
          <variants jsxoverflow="2"></variants>
          <strings jsxname="blkDeviceFooter" jsxwidth="100%" jsxheight="100%" jsxborder="1px solid #efefef;1px solid #9898a5;1px solid #9898a5;1px solid #d8d8e5" jsxtextalign="center"></strings>
          <dynamics jsxbgcolor="Dialog Footer"></dynamics>
          <object type="jsx3.gui.Block">
            <variants jsxoverflow="3" jsxheight="40" jsxrelativeposition="0" jsxleft="0" jsxtop="0"></variants>
            <strings jsxname="blkCancel" jsxwidth="100%" jsxdisplay="" jsxtextalign="right" jsxpadding="8 20 8 0"></strings>
            <object type="jsx3.gui.ImageButton">
              <variants jsxwidth="80" jsxheight="22" jsxtype="0" jsxprefetch="1" jsxstate="0"></variants>
              <strings jsxname="btnCancel" jsxtext="" jsximage="../../addins/ipvsCommon/images/buttons/btnCancelUp.png" jsxoverimage="../../addins/ipvsCommon/images/buttons/btnCancelOver.png" jsxdownimage="../../addins/ipvsCommon/images/buttons/btnCancelDown.png" jsxonimage="../../addins/ipvsCommon/images/buttons/btnCancelUp.png" jsxdisabledimage="../../addins/ipvsCommon/images/buttons/btnCancelDsbl.png" jsxtip="" jsxdisplay=""></strings>
            </object>
            <object type="jsx3.gui.ImageButton">
              <variants jsxwidth="80" jsxheight="22" jsxtype="0" jsxprefetch="1" jsxstate="0"></variants>
              <strings jsxname="btnDone" jsxtext="" jsximage="../../addins/ipvsCommon/images/buttons/btnDoneUp.png" jsxoverimage="../../addins/ipvsCommon/images/buttons/btnDoneOver.png" jsxdownimage="../../addins/ipvsCommon/images/buttons/btnDoneDown.png" jsxonimage="../../addins/ipvsCommon/images/buttons/btnDoneUp.png" jsxdisabledimage="../../addins/ipvsCommon/images/buttons/btnDoneDsbl.png" jsxtip="" jsxdisplay="none"></strings>
            </object>
          </object>
          <object type="jsx3.gui.Block">
            <variants jsxoverflow="3" jsxwidth="200"></variants>
            <strings jsxname="blkActions" jsxheight="100%" jsxrelativeposition="1"></strings>
            <object type="jsx3.gui.ImageButton">
              <variants jsxwidth="80" jsxheight="22" jsxtype="0" jsxprefetch="1" jsxstate="0" jsxenabled="0" jsxrelativeposition="0" jsxleft="20" jsxtop="8"></variants>
              <strings jsxname="btnPrevious" jsxtext="Previous screen" jsximage="../../addins/ipvsCommon/images/buttons/btnPreviousUp.png" jsxoverimage="../../addins/ipvsCommon/images/buttons/btnPreviousOver.png" jsxdownimage="../../addins/ipvsCommon/images/buttons/btnPreviousDown.png" jsxonimage="../../addins/ipvsCommon/images/buttons/btnPreviousUp.png" jsxdisabledimage="../../addins/ipvsCommon/images/buttons/btnPreviousDsbl.png" jsxmargin="0 10 0 10" jsxtip="" jsxdisplay="none"></strings>
            </object>
            <object type="jsx3.gui.ImageButton">
              <variants jsxwidth="80" jsxheight="22" jsxtype="0" jsxprefetch="1" jsxstate="0" jsxenabled="0" jsxrelativeposition="0" jsxleft="120" jsxtop="8" jsxzindex="10"></variants>
              <strings jsxname="btnNext" jsxtext="" jsximage="../../addins/ipvsCommon/images/buttons/btnNextUp.png" jsxoverimage="../../addins/ipvsCommon/images/buttons/btnNextOver.png" jsxdownimage="../../addins/ipvsCommon/images/buttons/btnNextDown.png" jsxonimage="../../addins/ipvsCommon/images/buttons/btnNextUp.png" jsxdisabledimage="../../addins/ipvsCommon/images/buttons/btnNextDsbl.png" jsxmargin="0 10 0 10" jsxtip="" jsxdisplay="none"></strings>
            </object>
            <object type="jsx3.gui.ImageButton">
              <variants jsxwidth="80" jsxheight="22" jsxtype="0" jsxprefetch="1" jsxstate="0" jsxenabled="0" jsxrelativeposition="0" jsxleft="120" jsxtop="8"></variants>
              <strings jsxname="btnSaveAssetInfo" jsxtext="" jsximage="../../addins/ipvsCommon/images/buttons/btnSaveUp.png" jsxoverimage="../../addins/ipvsCommon/images/buttons/btnSaveOver.png" jsxdownimage="../../addins/ipvsCommon/images/buttons/btnSaveDown.png" jsxonimage="../../addins/ipvsCommon/images/buttons/btnSaveUp.png" jsxdisabledimage="../../addins/ipvsCommon/images/buttons/btnSaveDsbl.png" jsxmargin="0 10 0 10" jsxtip="" jsxdisplay="none"></strings>
            </object>
          </object>
        </object>
      </object>
      <object type="jsx3.gui.Block">
        <variants jsxoverflow="2" jsxrelativeposition="0"></variants>
        <strings jsxwidth="100%" jsxheight="100%" jsxname="blkDeviceAdvancedSettings" jsxbg="background-image: url(JSXAPPS/IPVS_AdminUI/images/panels/mask60.png);" jsxtextalign="center" jsxcolor="" jsxdisplay="none"></strings>
        <dynamics jsxbgcolor="@Transparent BG"></dynamics>
        <object type="jsx3.gui.Block">
          <variants jsxoverflow="1" jsxloadtype="1" jsxrelativeposition="0" jsxleft="75" jsxtop="50"></variants>
          <strings jsxname="block" jsxwidth="70%" jsxheight="70%" jsxdisplay=""></strings>
          <dynamics jsxborder="Basic Border" jsxbgcolor="Dialog BG"></dynamics>
          <object type="jsx3.gui.LayoutGrid">
            <variants jsxrelativeposition="0" jsxleft="0" jsxtop="0" jsxoverflow="2"></variants>
            <strings jsxname="layoutRows" jsxrows="30,*,35" jsxwidth="100%" jsxheight="100%"></strings>
            <object type="jsx3.gui.Block">
              <variants jsxoverflow="2"></variants>
              <strings jsxname="pane0" jsxwidth="100%" jsxheight="100%" jsxtextalign="left" jsxbgcolor="#cccccc"></strings>
              <dynamics jsxborder="@Outset Top"></dynamics>
              <object type="jsx3.gui.Block">
                <variants jsxrelativeposition="0" jsxoverflow="3" jsxleft="9" jsxtop="0"></variants>
                <strings jsxname="h1" jsxtagname="h1" jsxtext="Advanced Settings" jsxdisplay="" jsxpadding="7"></strings>
              </object>
            </object>
            <object type="jsx3.gui.Block">
              <variants jsxoverflow="2"></variants>
              <strings jsxname="pane1" jsxwidth="100%" jsxheight="100%" jsxborder="0px solid ;0px solid ;1px solid #bbbbbb;0px solid" jsxpadding="20 10 10 10"></strings>
              <object type="jsx3.gui.Block">
                <variants jsxoverflow="2" jsxheight="210"></variants>
                <strings jsxname="blkFormDeviceDesc" jsxwidth="100%" jsxrelativeposition="1"></strings>
                <object type="jsx3.gui.Block">
                  <variants jsxrelativeposition="1" jsxoverflow="3" jsxheight="210" jsxfontsize="11"></variants>
                  <strings jsxname="label" jsxtext="Device Private Data:" jsxwidth="25%" jsxtextalign="right" jsxpadding="6 0 6 0" jsxfontweight="bold" jsxcolor="#666666"></strings>
                </object>
                <object type="jsx3.gui.Block">
                  <variants jsxoverflow="3" jsxheight="210"></variants>
                  <strings jsxname="blkField" jsxwidth="74%" jsxrelativeposition="1" jsxpadding="6 2 2 10"></strings>
                  <object type="jsx3.gui.TextBox">
                    <variants jsxheight="200" jsxtype="1" jsxrelativeposition="1"></variants>
                    <strings jsxwidth="90%" jsxname="txtAssetDevicePrivateData" jsxmargin="0 4 0 0" jsxdisplay="" jsxvalue=""></strings>
                    <dynamics jsxfontsize="SmallText"></dynamics>
                  </object>
                </object>
              </object>
            </object>
            <object type="jsx3.gui.Block">
              <variants jsxoverflow="2"></variants>
              <strings jsxname="pane2" jsxwidth="100%" jsxheight="100%" jsxtextalign="right" jsxpadding="6 20 6 6"></strings>
              <dynamics jsxborder="@Outset Top"></dynamics>
              <object type="jsx3.gui.ImageButton">
                <variants jsxwidth="80" jsxheight="22" jsxtype="0" jsxprefetch="1" jsxstate="0"></variants>
                <strings jsxname="imgAdvanceSettingsDone" jsximage="../../addins/ipvsCommon/images/buttons/btnDoneUp.png"></strings>
              </object>
            </object>
          </object>
        </object>
      </object>
    </object>
  </object>
</serialization>