<?xml version="1.0"?><!--
  ~ Copyright (c) 2001-2007, TIBCO Software Inc.
  ~ Use, modification, and distribution subject to terms of license.
  --><data jsxid="jsxroot" jsxnamespace="jsx3.ide.mapper.Mapper" jsxversion="1.0"><record jsxid="x14801" jsxtext="Operation (Transaction)" type="T" jsxopen="1" opname="jsxtransaction" jsxselected="1"><headers jsxid="x83471"><record jsxid="x62686" name="Content-Type" value="text/xml"/></headers><record jsxid="x75977" jsxtext="Input (request)" type="I" jsxopen="1" src="../IPVS-Common/model/xsd/mediaroom.xsd"><record jsxid="x29911" jsxtext="MediaStreamFilter" jsxopen="1" type="C" path="/jsx1:schema/jsx1:schema[24]/jsx1:element[4]" datatype="MediaStreamFilterType" ttns="" tns=""><record jsxid="x41837" jsxtext="Name" jsxopen="1" type="E" path="/jsx1:schema/jsx1:schema[19]/jsx1:complexType[4]/jsx1:sequence/jsx1:element" datatype="string" simple="1"/><record jsxid="x70323" jsxtext="Description" jsxopen="1" type="E" path="/jsx1:schema/jsx1:schema[19]/jsx1:complexType[4]/jsx1:sequence/jsx1:element[2]" datatype="string" simple="1"><restrictions jsxid="x54369"><record jsxid="x12108" name="minoccur" value="0"/></restrictions></record><record jsxid="x21180" jsxtext="Version" jsxopen="1" type="C" path="/jsx1:schema/jsx1:schema[27]/jsx1:attributeGroup[10]" datatype="" ref="1" groupref="1"><record jsxid="x17737" jsxtext="Version" jsxopen="1" type="A" path="/jsx1:schema/jsx1:schema[27]/jsx1:attributeGroup[10]/jsx1:attribute" datatype="double" simple="1" jsxSelectMask="Script"><mappings jsxid="x87167"><record jsxid="jsx_6p" name="Script" value="setValue(&quot;1.1&quot;);"/></mappings></record><record jsxid="x65815" jsxtext="Revision" jsxopen="1" type="A" path="/jsx1:schema/jsx1:schema[27]/jsx1:attributeGroup[10]/jsx1:attribute[2]" datatype="int" simple="1" jsxSelectMask="Script"><mappings jsxid="x21016"><record jsxid="jsx_6q" name="Script" value="setValue(&quot;1&quot;);"/></mappings></record></record><record jsxid="x55577" jsxtext="AutoNID-NoParse" jsxopen="1" type="C" path="/jsx1:schema/jsx1:schema[27]/jsx1:attributeGroup" datatype="" ref="1" groupref="1" jsxSelectMask="Script"><record jsxid="x34014" jsxtext="Parse" jsxopen="1" type="A" path="/jsx1:schema/jsx1:schema[27]/jsx1:attributeGroup/jsx1:attribute" datatype="boolean" simple="1"/><record jsxid="x20927" jsxtext="NIDScheme" jsxopen="1" type="A" path="/jsx1:schema/jsx1:schema[27]/jsx1:attributeGroup/jsx1:attribute[2]" datatype="string" simple="1"/><record jsxid="x62863" jsxtext="NID" jsxopen="1" type="A" path="/jsx1:schema/jsx1:schema[27]/jsx1:attributeGroup/jsx1:attribute[3]" datatype="string" simple="1"/></record><record jsxid="x96265" jsxtext="SrcFilterSet" jsxopen="1" type="C" path="/jsx1:schema/jsx1:schema[24]/jsx1:complexType[7]/jsx1:complexContent/jsx1:extension/jsx1:sequence/jsx1:element" datatype="SrcFilterSetType" ttns="" jsxSelectMask="Script"><record jsxid="x83225" jsxtext="SrcFilter" jsxopen="1" type="C" path="/jsx1:schema/jsx1:schema[24]/jsx1:complexType[8]/jsx1:sequence/jsx1:element" datatype="MediaStreamSrcDstFilterType" ttns="" jsxSelectMask="Script"><restrictions jsxid="x60332"><record jsxid="x2799" name="maxoccur" value="unbounded"/></restrictions><record jsxid="x11844" jsxtext="UserFilterNID" jsxopen="1" type="E" path="/jsx1:schema/jsx1:schema[24]/jsx1:complexType[12]/jsx1:sequence/jsx1:sequence/jsx1:element" datatype="string" simple="1"/><record jsxid="x39983" jsxtext="MediaStreamResourceFilterNID" jsxopen="1" type="E" path="/jsx1:schema/jsx1:schema[24]/jsx1:complexType[12]/jsx1:sequence/jsx1:sequence[2]/jsx1:element" datatype="string" simple="1"/></record></record><record jsxid="x88716" jsxtext="DstFilterSet" jsxopen="1" type="C" path="/jsx1:schema/jsx1:schema[24]/jsx1:complexType[7]/jsx1:complexContent/jsx1:extension/jsx1:sequence/jsx1:element[2]" datatype="DstFilterSetType" ttns="" jsxSelectMask="Script"><record jsxid="x74329" jsxtext="DstFilter" jsxopen="1" type="C" path="/jsx1:schema/jsx1:schema[24]/jsx1:complexType[9]/jsx1:sequence/jsx1:element" datatype="MediaStreamSrcDstFilterType" ttns="" jsxSelectMask="Script"><restrictions jsxid="x68714"><record jsxid="x17985" name="maxoccur" value="unbounded"/></restrictions><record jsxid="x90780" jsxtext="UserFilterNID" jsxopen="1" type="E" path="/jsx1:schema/jsx1:schema[24]/jsx1:complexType[12]/jsx1:sequence/jsx1:sequence/jsx1:element" datatype="string" simple="1"/><record jsxid="x11793" jsxtext="MediaStreamResourceFilterNID" jsxopen="1" type="E" path="/jsx1:schema/jsx1:schema[24]/jsx1:complexType[12]/jsx1:sequence/jsx1:sequence[2]/jsx1:element" datatype="string" simple="1"/></record></record><record jsxid="x27821" jsxtext="RelayFlag" jsxopen="1" type="E" path="/jsx1:schema/jsx1:schema[24]/jsx1:complexType[7]/jsx1:complexContent/jsx1:extension/jsx1:sequence/jsx1:element[3]" datatype="string" simple="1" jsxSelectMask="Script"><restrictions jsxid="x10450"><record jsxid="x11802" name="enumeration" value="SrcRelay"/><record jsxid="x45977" name="enumeration" value="DstRelay"/><record jsxid="x53945" name="enumeration" value="DirectConnect"/></restrictions></record><record jsxid="x68661" jsxtext="RelayFilterSet" jsxopen="1" type="C" path="/jsx1:schema/jsx1:schema[24]/jsx1:complexType[7]/jsx1:complexContent/jsx1:extension/jsx1:sequence/jsx1:element[4]" datatype="RelayFilterSetType" ttns="" jsxSelectMask="Script"><record jsxid="x50495" jsxtext="RelayFilter" jsxopen="1" type="C" path="/jsx1:schema/jsx1:schema[24]/jsx1:complexType[10]/jsx1:sequence/jsx1:element" datatype="MediaStreamSrcDstFilterType" ttns="" jsxSelectMask="Script"><restrictions jsxid="x77311"><record jsxid="x9211" name="maxoccur" value="unbounded"/></restrictions><record jsxid="x5241" jsxtext="UserFilterNID" jsxopen="1" type="E" path="/jsx1:schema/jsx1:schema[24]/jsx1:complexType[12]/jsx1:sequence/jsx1:sequence/jsx1:element" datatype="string" simple="1"/><record jsxid="x72839" jsxtext="MediaStreamResourceFilterNID" jsxopen="1" type="E" path="/jsx1:schema/jsx1:schema[24]/jsx1:complexType[12]/jsx1:sequence/jsx1:sequence[2]/jsx1:element" datatype="string" simple="1"/></record></record><record jsxid="x97611" jsxtext="PVRFilterSet" jsxopen="1" type="C" path="/jsx1:schema/jsx1:schema[24]/jsx1:complexType[7]/jsx1:complexContent/jsx1:extension/jsx1:sequence/jsx1:element[5]" datatype="PVRFilterSetType" ttns="" jsxSelectMask="Script"><restrictions jsxid="x42251"><record jsxid="x34665" name="minoccur" value="0"/></restrictions><record jsxid="x75232" jsxtext="PVRFilter" jsxopen="1" type="C" path="/jsx1:schema/jsx1:schema[24]/jsx1:complexType[11]/jsx1:sequence/jsx1:element" datatype="MediaStreamSrcDstFilterType" ttns="" jsxSelectMask="Script"><restrictions jsxid="x44565"><record jsxid="x34780" name="maxoccur" value="unbounded"/></restrictions><record jsxid="x18577" jsxtext="UserFilterNID" jsxopen="1" type="E" path="/jsx1:schema/jsx1:schema[24]/jsx1:complexType[12]/jsx1:sequence/jsx1:sequence/jsx1:element" datatype="string" simple="1"/><record jsxid="x86944" jsxtext="MediaStreamResourceFilterNID" jsxopen="1" type="E" path="/jsx1:schema/jsx1:schema[24]/jsx1:complexType[12]/jsx1:sequence/jsx1:sequence[2]/jsx1:element" datatype="string" simple="1"/></record></record><record jsxid="x49936" jsxtext="ProfileFilterSet" jsxopen="1" type="C" path="/jsx1:schema/jsx1:schema[24]/jsx1:complexType[7]/jsx1:complexContent/jsx1:extension/jsx1:sequence/jsx1:element[6]" datatype="ProfileFilterSetType" ttns="" jsxSelectMask="Script"><record jsxid="x97664" jsxtext="ProfileFilter" jsxopen="1" type="C" path="/jsx1:schema/jsx1:schema[24]/jsx1:complexType[13]/jsx1:sequence/jsx1:element" datatype="MediaStreamProfileFilterType" ttns="" jsxSelectMask="Script"><restrictions jsxid="x57260"><record jsxid="x44740" name="maxoccur" value="unbounded"/></restrictions><record jsxid="x97135" jsxtext="MediaStreamProfileFilterNID" jsxopen="1" type="E" path="/jsx1:schema/jsx1:schema[24]/jsx1:complexType[14]/jsx1:sequence/jsx1:element" datatype="string" simple="1"/></record></record><record jsxid="x37545" jsxtext="RuleKeyTagFilterSet" jsxopen="1" type="C" path="/jsx1:schema/jsx1:schema[24]/jsx1:complexType[7]/jsx1:complexContent/jsx1:extension/jsx1:sequence/jsx1:element[7]" datatype="MediaRoomRuleKeyTagFilterSetType" ttns="" jsxSelectMask="Script"><record jsxid="x11702" jsxtext="RuleKeyTagFilter" jsxopen="1" type="C" path="/jsx1:schema/jsx1:schema[24]/jsx1:complexType[17]/jsx1:sequence/jsx1:element" datatype="MediaRoomRuleKeyTagFilterType" ttns="" jsxSelectMask="Script"><restrictions jsxid="x15296"><record jsxid="x3267" name="maxoccur" value="unbounded"/></restrictions><record jsxid="x79384" jsxtext="RuleKeyLHTagName" jsxopen="1" type="C" path="/jsx1:schema/jsx1:schema[24]/jsx1:complexType[18]/jsx1:sequence/jsx1:element" datatype="MediaRoomRuleKeyTagSpecType" ttns="" jsxSelectMask="Script"><record jsxid="x61207" jsxtext="RuleKey" jsxopen="1" type="E" path="/jsx1:schema/jsx1:schema[24]/jsx1:simpleType" datatype="MediaRoomRuleKeyEnumType" ttns="" jsxSelectMask="Script"/><record jsxid="x34628" jsxtext="TagName" jsxopen="1" type="E" path="/jsx1:schema/jsx1:schema[24]/jsx1:complexType[19]/jsx1:sequence/jsx1:element[2]" datatype="string" simple="1"/></record><record jsxid="x60001" jsxtext="MatchOp" jsxopen="1" type="E" path="/jsx1:schema/jsx1:schema[19]/jsx1:simpleType[2]" datatype="MatchOpEnumType" ttns="" jsxSelectMask="Script"/><record jsxid="x33475" jsxtext="RuleKeyRHTagName" jsxopen="1" type="C" path="/jsx1:schema/jsx1:schema[24]/jsx1:complexType[18]/jsx1:sequence/jsx1:element[3]" datatype="MediaRoomRuleKeyTagSpecType" ttns="" jsxSelectMask="Script"><record jsxid="x46138" jsxtext="RuleKey" jsxopen="1" type="E" path="/jsx1:schema/jsx1:schema[24]/jsx1:simpleType" datatype="MediaRoomRuleKeyEnumType" ttns="" jsxSelectMask="Script"/><record jsxid="x58068" jsxtext="TagName" jsxopen="1" type="E" path="/jsx1:schema/jsx1:schema[24]/jsx1:complexType[19]/jsx1:sequence/jsx1:element[2]" datatype="string" simple="1"/></record></record></record></record></record><record jsxid="x8057" jsxtext="Output (response)" type="O" jsxopen="1"/></record></data>