<?xml version="1.0"?><!--
  ~ Copyright (c) 2001-2007, TIBCO Software Inc.
  ~ Use, modification, and distribution subject to terms of license.
  --><data jsxid="jsxroot" jsxnamespace="jsx3.ide.mapper.Mapper" jsxversion="1.0"><record jsxid="x20804" jsxtext="Operation (Transaction)" type="T" jsxopen="1" opname="jsxtransaction"><headers jsxid="x77592"><record jsxid="x74994" name="Content-Type" value="text/xml"/></headers><record jsxid="x93596" jsxtext="Input (request)" type="I" jsxopen="1" src="../IPVS-Common/model/xsd/mediaroom.xsd"><record jsxid="x12646" jsxtext="Report" jsxopen="1" type="C" path="/jsx1:schema/jsx1:schema[40]/jsx1:element[2]" datatype="ReportType" ttns="" tns=""><record jsxid="x52562" jsxtext="serviceVer" jsxopen="1" type="A" path="/jsx1:schema/jsx1:schema[40]/jsx1:complexType[2]/jsx1:attribute" datatype="double" simple="1"/><record jsxid="x21452" jsxtext="Ver" jsxopen="1" type="A" path="/jsx1:schema/jsx1:schema[40]/jsx1:complexType[2]/jsx1:attribute[2]" datatype="double" simple="1" jsxSelectMask="Script"><mappings jsxid="x54457"><record jsxid="jsx_3c" name="Script" value="setValue(&quot;1.3&quot;);"/></mappings></record><record jsxid="x49639" jsxtext="Rev" jsxopen="1" type="A" path="/jsx1:schema/jsx1:schema[40]/jsx1:complexType[2]/jsx1:attribute[3]" datatype="int" simple="1" jsxSelectMask="Script"><mappings jsxid="x25741"><record jsxid="jsx_3d" name="Script" value="setValue(&quot;1&quot;);"/></mappings></record><record jsxid="x74133" jsxtext="NID" jsxopen="1" type="A" path="/jsx1:schema/jsx1:schema[37]/jsx1:attributeGroup/jsx1:attribute" datatype="string" simple="1"/><record jsxid="x62480" jsxtext="parentNID" jsxopen="1" type="A" path="/jsx1:schema/jsx1:schema[37]/jsx1:attributeGroup/jsx1:attribute[2]" datatype="string" simple="1"/><record jsxid="x3764" jsxtext="Type" jsxopen="1" type="E" path="/jsx1:schema/jsx1:schema[5]/jsx1:simpleType[13]" datatype="ReportEnumType" ttns="" jsxSelectMask="Script"/><record jsxid="x73137" jsxtext="Name" jsxopen="1" type="E" path="/jsx1:schema/jsx1:schema[40]/jsx1:complexType[2]/jsx1:sequence/jsx1:element[2]" datatype="string" simple="1"/><record jsxid="x43732" jsxtext="Description" jsxopen="1" type="E" path="/jsx1:schema/jsx1:schema[40]/jsx1:complexType[2]/jsx1:sequence/jsx1:element[3]" datatype="string" simple="1"/><record jsxid="x10437" jsxtext="ReportExport" jsxopen="1" type="C" path="/jsx1:schema/jsx1:schema[40]/jsx1:complexType[2]/jsx1:sequence/jsx1:element[4]" datatype="ReportExportType" ttns="" jsxSelectMask="Script"><record jsxid="x46129" jsxtext="EnableExport" jsxopen="1" type="E" path="/jsx1:schema/jsx1:schema[40]/jsx1:complexType[3]/jsx1:sequence/jsx1:element" datatype="boolean" simple="1"/><record jsxid="x56965" jsxtext="ExportSchedule" jsxopen="1" type="E" path="/jsx1:schema/jsx1:schema[40]/jsx1:complexType[3]/jsx1:sequence/jsx1:element[2]" datatype="integer" simple="1"/><record jsxid="x68223" jsxtext="ExportURL" jsxopen="1" type="E" path="/jsx1:schema/jsx1:schema[40]/jsx1:complexType[3]/jsx1:sequence/jsx1:element[3]" datatype="string" simple="1"/></record><record jsxid="x35291" jsxtext="ReportConfig" jsxopen="1" type="C" path="/jsx1:schema/jsx1:schema[40]/jsx1:complexType[2]/jsx1:sequence/jsx1:element[5]" datatype="ReportConfigType" ttns="" jsxSelectMask="Script"><record jsxid="x23206" jsxtext="PolicyReportConfig" jsxopen="1" type="C" path="/jsx1:schema/jsx1:schema[40]/jsx1:complexType[4]/jsx1:sequence/jsx1:choice/jsx1:element" datatype="PolicyReportConfigType" ttns="" jsxSelectMask="Script"><record jsxid="x5994" jsxtext="SelectFormatXSL" jsxopen="1" type="E" path="/jsx1:schema/jsx1:schema[40]/jsx1:complexType[7]/jsx1:sequence/jsx1:element" datatype="string" simple="1"/><record jsxid="x59364" jsxtext="selectFormat" jsxopen="1" type="A" path="/jsx1:schema/jsx1:schema[40]/jsx1:complexType[7]/jsx1:attribute" datatype="string" simple="1"/><record jsxid="x23589" jsxtext="selectProperties" jsxopen="1" type="A" path="/jsx1:schema/jsx1:schema[40]/jsx1:complexType[7]/jsx1:attribute[2]" datatype="string" simple="1"/><record jsxid="x88422" jsxtext="selectPermissions" jsxopen="1" type="A" path="/jsx1:schema/jsx1:schema[40]/jsx1:complexType[5]/jsx1:complexContent/jsx1:extension/jsx1:attribute" datatype="string" simple="1"/><record jsxid="x87954" jsxtext="whereTextSubStr" jsxopen="1" type="A" path="/jsx1:schema/jsx1:schema[40]/jsx1:complexType[5]/jsx1:complexContent/jsx1:extension/jsx1:attribute[2]" datatype="string" simple="1"/><record jsxid="x33246" jsxtext="whereTagExpr" jsxopen="1" type="A" path="/jsx1:schema/jsx1:schema[40]/jsx1:complexType[5]/jsx1:complexContent/jsx1:extension/jsx1:attribute[3]" datatype="string" simple="1"/><record jsxid="x29404" jsxtext="whereTagExprMode" jsxopen="1" type="A" path="/jsx1:schema/jsx1:schema[40]/jsx1:complexType[5]/jsx1:complexContent/jsx1:extension/jsx1:attribute[4]" datatype="TagExprModeType" simple="1"/><record jsxid="x6547" jsxtext="whereTarget" jsxopen="1" type="A" path="/jsx1:schema/jsx1:schema[40]/jsx1:complexType[5]/jsx1:complexContent/jsx1:extension/jsx1:attribute[5]" datatype="TargetEnumType" simple="1"/></record><record jsxid="x98729" jsxtext="AuditReportConfig" jsxopen="1" type="C" path="/jsx1:schema/jsx1:schema[40]/jsx1:complexType[4]/jsx1:sequence/jsx1:choice/jsx1:element[2]" datatype="AuditReportConfigType" ttns="" jsxSelectMask="Script"><record jsxid="x23277" jsxtext="SelectFormatXSL" jsxopen="1" type="E" path="/jsx1:schema/jsx1:schema[40]/jsx1:complexType[7]/jsx1:sequence/jsx1:element" datatype="string" simple="1"/><record jsxid="x57871" jsxtext="selectFormat" jsxopen="1" type="A" path="/jsx1:schema/jsx1:schema[40]/jsx1:complexType[7]/jsx1:attribute" datatype="string" simple="1"/><record jsxid="x66797" jsxtext="selectProperties" jsxopen="1" type="A" path="/jsx1:schema/jsx1:schema[40]/jsx1:complexType[7]/jsx1:attribute[2]" datatype="string" simple="1"/></record></record><record jsxid="x36823" jsxtext="ReportStatus" jsxopen="1" type="C" path="/jsx1:schema/jsx1:schema[40]/jsx1:complexType[2]/jsx1:sequence/jsx1:element[6]" datatype="ReportStatusType" ttns="" jsxSelectMask="Script"><record jsxid="x38908" jsxtext="LastExportStatus" jsxopen="1" type="C" path="/jsx1:schema/jsx1:schema[40]/jsx1:complexType[8]/jsx1:sequence/jsx1:element" datatype="ReportStatusInfoType" ttns="" jsxSelectMask="Script"><record jsxid="x72106" jsxtext="date" jsxopen="1" type="A" path="/jsx1:schema/jsx1:schema[40]/jsx1:complexType[10]/jsx1:attribute" datatype="string" simple="1"/><record jsxid="x2627" jsxtext="time" jsxopen="1" type="A" path="/jsx1:schema/jsx1:schema[40]/jsx1:complexType[10]/jsx1:attribute[2]" datatype="string" simple="1"/><record jsxid="x90693" jsxtext="state" jsxopen="1" type="A" path="/jsx1:schema/jsx1:schema[40]/jsx1:complexType[9]/jsx1:complexContent/jsx1:extension/jsx1:attribute" datatype="ReportStateEnumType" simple="1"/></record><record jsxid="x93954" jsxtext="LastExported" jsxopen="1" type="C" path="/jsx1:schema/jsx1:schema[40]/jsx1:complexType[8]/jsx1:sequence/jsx1:element[2]" datatype="DateTimeAttrType" ttns="" jsxselected="1"><record jsxid="x60144" jsxtext="date" jsxopen="1" type="A" path="/jsx1:schema/jsx1:schema[40]/jsx1:complexType[10]/jsx1:attribute" datatype="string" simple="1"/><record jsxid="x62719" jsxtext="time" jsxopen="1" type="A" path="/jsx1:schema/jsx1:schema[40]/jsx1:complexType[10]/jsx1:attribute[2]" datatype="string" simple="1"/></record></record></record></record><record jsxid="x43308" jsxtext="Output (response)" type="O" jsxopen="1"/></record></data>