<serialization xmlns="urn:tibco.com/v3.0">
  <name><![CDATA[CanvasEditorWindowPanel]]></name>
  <description><![CDATA[A com.ipvs.gui.CanvasEditorWindowPanel object.]]></description>
  <object type="com.ipvs.gui.CanvasEditorWindowPanel">
    <strings jsxname=" CanvasEditorWindowPanel" jsxwidth="100%" jsxheight="100%" jsxtext="[Text]" jsxxmlurl="jsxaddin://user!ipvsCommon/xml/CanvasEditorWindowPanel.xml" jsxbgcolor="#262626" jsxclassoff="endpoint" jsxclasson="endpointSelected" jsxclassover="endpointOver" jsxtype="0"/>
    <events jsxselect="alert('End Point Block: Select');"/>
  </object>
</serialization>