<?xml version="1.0" encoding="UTF-8"?>
<ConnectionStateList>
	<ConnectionState state="CREATED"  desc="STREAM_STOPPED" streamstate="0"/>
    <ConnectionState state="AUTHORIZING"  desc="WAITING_FOR_XAUTH" streamstate="1"/>
    <ConnectionState state="CHECKING_AVAILABILITY"  desc="WAITING_FOR_CONTACTJID" streamstate="2"/>
    <ConnectionState state="WAITING_FOR_DEST"  desc="WAITING_FOR_DEST" streamstate="3"/>
    <ConnectionState state="WAITING_FOR_SOURCE-DEST_CONTACTED"  desc="WATCH_SENTTO_DEST" streamstate="4"/>
    <ConnectionState state="WAITING_FOR_SOURCE-DEST_ACKNOWLEDGED"  desc="WAITING_FOR_SOURCE" streamstate="5"/>
    <ConnectionState state="WAITING_FOR_STREAMURL"  desc="WAITING_FOR_STREAMURL" streamstate="6"/>
    <ConnectionState state="WAITING_FOR_STREAMSTART"  desc="WAITING_FOR_STREAMSTARTED" streamstate="7"/>
    <ConnectionState state="STREAMING"  desc="STREAM_STARTED" streamstate="8"/>
    <ConnectionState state="STREAM_PAUSED"  desc="STREAM_PAUSED" streamstate="9"/>
    <ConnectionState state="DENIED_XAUTH"  desc="DENIED_XAUTH" streamstate="10"/>
    <ConnectionState state="REVOKED_XAUTH"  desc="REVOKED_XAUTH" streamstate="11"/>
    <ConnectionState state="END_OF_MEDIA"  desc="END_OF_MEDIA" streamstate="12"/>
    <ConnectionState state="SETUP_ERROR"  desc="SETUP_ERROR" streamstate="201"/>
    <ConnectionState state="START_ERROR"  desc="START_ERROR" streamstate="202"/>
    <ConnectionState state="SOURCE_ERROR"  desc="SOURCE_ERROR" streamstate="203"/>
    <ConnectionState state="MEDIA_ERROR"  desc="MEDIA_ERROR" streamstate="204"/>
    <ConnectionState state="DEST_ERROR"  desc="DEST_ERROR" streamstate="205"/>    
	<ConnectionState state="DELETED"  desc="STREAM_DELETED" streamstate="-1"/>
</ConnectionStateList>
